thelabdb/__init__.py
thelabdb/apps.py
thelabdb/py.typed
thelabdb/fields/__init__.py
thelabdb/fields/char.py
thelabdb/fields/fernet.py
thelabdb/fields/hkdf.py
thelabdb/fields/pydantic.py
thelabdb/pgviews/__init__.py
thelabdb/pgviews/apps.py
thelabdb/pgviews/models.py
thelabdb/pgviews/signals.py
thelabdb/pgviews/view.py
thelabdb/pgviews/db/__init__.py
thelabdb/pgviews/db/sql/__init__.py
thelabdb/pgviews/db/sql/compiler.py
thelabdb/pgviews/db/sql/query.py
thelabdb/pgviews/management/__init__.py
thelabdb/pgviews/management/commands/__init__.py
thelabdb/pgviews/management/commands/clear_pgviews.py
thelabdb/pgviews/management/commands/sync_pgviews.py
thelabdb/tests/__init__.py
thelabdb/tests/settings/__init__.py
thelabdb/tests/settings/docgen_setup.py
thelabdb/tests/settings/pg.py
thelabdb/tests/settings/sqlite.py
thelabdb/tests/testspg/__init__.py
thelabdb/tests/testspg/apps.py
thelabdb/tests/testspg/models.py
thelabdb/tests/testspg/test_pgviews.py
thelabdb/tests/testspg/migrations/0001_initial.py
thelabdb/tests/testspg/migrations/__init__.py
thelabdb/tests/testsuniv/__init__.py
thelabdb/tests/testsuniv/apps.py
thelabdb/tests/testsuniv/models.py
thelabdb/tests/testsuniv/test_char_fields.py
thelabdb/tests/testsuniv/test_fernet_fields.py
thelabdb/tests/testsuniv/test_newtype_fields.py
thelabdb/tests/testsuniv/test_pydantic_field.py
thelabdb/tests/testsuniv/migrations/0001_initial.py
thelabdb/tests/testsuniv/migrations/0002_product.py
thelabdb/tests/testsuniv/migrations/0003_store_inventory.py
thelabdb/tests/testsuniv/migrations/0004_nullchar_uppercasechar.py
thelabdb/tests/testsuniv/migrations/__init__.py
thelabdb-0.6.1.dist-info/METADATA
thelabdb-0.6.1.dist-info/WHEEL
thelabdb-0.6.1.dist-info/licenses/LICENSE
thelabdb-0.6.1.dist-info/RECORD
